coversnap-0.0.4.dist-info/METADATA
coversnap-0.0.4.dist-info/WHEEL
coversnap-0.0.4.dist-info/entry_points.txt
coversnap-0.0.4.dist-info/licenses/LICENSE
coversnap/__init__.py
coversnap/__main__.py
coversnap/capture.py
coversnap-0.0.4.dist-info/RECORD
